pyov2/__init__.py
pyov2/file.py
pyov2/ov2.py
pyov2-1.0.1.dist-info/LICENSE
pyov2-1.0.1.dist-info/METADATA
pyov2-1.0.1.dist-info/WHEEL
pyov2-1.0.1.dist-info/top_level.txt
pyov2-1.0.1.dist-info/RECORD
