Metadata-Version: 2.1
Name: pyov2
Version: 1.0.1
Summary: Python module used to generate ov2 poi (point of interest) files
Home-page: https://github.com/botenvouwer/pyov2
Author: William Loosman
Author-email: william.wl@live.nl
Project-URL: Bug Tracker, https://github.com/botenvouwer/pyov2/issues
Classifier: Programming Language :: Python :: 3
Classifier: License :: OSI Approved :: MIT License
Classifier: Operating System :: OS Independent
Requires-Python: >=3.6
License-File: LICENSE
